core/__init__.py
core/_internals/__init__.py
core/_internals/application/__init__.py
core/_internals/application/use_cases/__init__.py
core/_internals/application/use_cases/rate_limit.py
core/_internals/domain/__init__.py
core/_internals/domain/enums/__init__.py
core/_internals/domain/enums/storage.py
core/_internals/domain/exceptions/__init__.py
core/_internals/domain/exceptions/exception.py
core/_internals/domain/interfaces/__init__.py
core/_internals/domain/interfaces/rate_limit.py
core/_internals/domain/interfaces/storage.py
core/_internals/domain/models/__init__.py
core/_internals/domain/models/bucket.py
core/_internals/domain/models/rate_limit_result.py
core/_internals/domain/models/window.py
core/_internals/domain/services/__init__.py
core/_internals/domain/services/algorithm/__init__.py
core/_internals/domain/services/algorithm/sliding_window_counter.py
core/_internals/domain/services/algorithm/sliding_window_log.py
core/_internals/domain/services/algorithm/token_bucket.py
core/_internals/infrastructure/__init__.py
core/_internals/infrastructure/storage/__init__.py
core/_internals/infrastructure/storage/in_mem/__init__.py
core/_internals/infrastructure/storage/in_mem/repo/__init__.py
core/_internals/infrastructure/storage/in_mem/repo/in_mem_impl.py
core/_internals/infrastructure/storage/redis/__init__.py
core/_internals/infrastructure/storage/redis/redis.py
core/_internals/infrastructure/storage/redis/repo/__init__.py
core/_internals/infrastructure/storage/redis/repo/redis_impl.py
core/_internals/infrastructure/throtty/__init__.py
core/_internals/infrastructure/throtty/core.py
core/limiter.py
throtty-0.0.1.dist-info/METADATA
throtty-0.0.1.dist-info/WHEEL
throtty-0.0.1.dist-info/licenses/LICENSE
throtty-0.0.1.dist-info/RECORD
