Metadata-Version: 2.4
Name: throtty
Version: 0.0.1
Summary: Rate limit library for ASGI application
License: MIT
License-File: LICENSE
Author: DickyAdi
Author-email: dickyadi44@gmail.com
Requires-Python: >=3.12,<4.0
Classifier: License :: OSI Approved :: MIT License
Classifier: Programming Language :: Python :: 3
Classifier: Programming Language :: Python :: 3.12
Classifier: Programming Language :: Python :: 3.13
Classifier: Programming Language :: Python :: 3.14
Requires-Dist: redis (>=7.0.1,<8.0.0)
Requires-Dist: sortedcontainers (>=2.4.0,<3.0.0)
